libwinmedia/__init__.py
libwinmedia/library.py
libwinmedia/media.py
libwinmedia/nativecontrols.py
libwinmedia/player.py
libwinmedia/playlist.py
libwinmedia/tags.py
libwinmedia-1.0.1.dist-info/LICENSE
libwinmedia-1.0.1.dist-info/METADATA
libwinmedia-1.0.1.dist-info/WHEEL
libwinmedia-1.0.1.dist-info/top_level.txt
libwinmedia-1.0.1.dist-info/RECORD
