Metadata-Version: 2.1
Name: libwinmedia
Version: 1.0.1
Summary: Python bindings for libwinmedia, a tiny yet powerful media playback library for Windows and Linux.
Home-page: https://github.com/libwinmedia/libwinmedia-py
Author: libwinmedia Team
Author-email: mytja@protonmail.com
License: MIT
Platform: UNKNOWN
Classifier: Topic :: Multimedia :: Sound/Audio
Classifier: Operating System :: POSIX :: Linux
Classifier: Operating System :: Microsoft :: Windows :: Windows 10
Classifier: Operating System :: Microsoft :: Windows
Classifier: Topic :: Multimedia :: Video
Classifier: License :: OSI Approved :: MIT License
Requires-Dist: PyGObject ; platform_system == "Linux"
